pytest_spiratest_integration.py
pytest_spiratest-1.4.1.dist-info/LICENSE
pytest_spiratest-1.4.1.dist-info/METADATA
pytest_spiratest-1.4.1.dist-info/WHEEL
pytest_spiratest-1.4.1.dist-info/entry_points.txt
pytest_spiratest-1.4.1.dist-info/top_level.txt
pytest_spiratest-1.4.1.dist-info/RECORD
