Metadata-Version: 2.1
Name: pytest-spiratest
Version: 1.4.1
Summary: Exports unit tests as test runs in SpiraTest/Team/Plan
Home-page: http://www.inflectra.com/SpiraTest/Integrations/Unit-Test-Frameworks.aspx
Author: Inflectra Corporation
Author-email: support@inflectra.com
License: UNKNOWN
Platform: UNKNOWN
Classifier: Framework :: Pytest
Classifier: Topic :: Software Development :: Testing
Classifier: Programming Language :: Python :: 3
Classifier: Operating System :: OS Independent
License-File: LICENSE
